adix/__init__.py
adix/configs.py
adix/datahub.py
adix/dtype.py
adix/wizrenderer.py
adix/datasets/__init__.py
adix/datasets/titanic.csv
adix/processing/__init__.py
adix/processing/tables.py
adix/processing/wiz.py
adix/processing/calc/__init__.py
adix/processing/calc/operations.py
adix-0.2.6.dist-info/LICENSE.txt
adix-0.2.6.dist-info/METADATA
adix-0.2.6.dist-info/WHEEL
adix-0.2.6.dist-info/top_level.txt
adix-0.2.6.dist-info/RECORD
