Metadata-Version: 2.1
Name: adix
Version: 0.2.6
Summary: Automated exploratory data analysis (EDA).
Author: Marek Jindrich
Author-email: adix.eda@gmail.com
Project-URL: Homepage, https://imooger.github.io
Project-URL: Documentation, https://imooger.github.io
Project-URL: Repository, https://github.com/imooger/adix
Project-URL: Bug Tracker, https://github.com/imooger/adix/issues
Keywords: pandas eda data data-science data-analysis python jupyter ipython
Classifier: Development Status :: 4 - Beta
Classifier: License :: OSI Approved :: MIT License
Classifier: Environment :: Console
Classifier: Operating System :: OS Independent
Classifier: Intended Audience :: Science/Research
Classifier: Intended Audience :: Developers
Classifier: Intended Audience :: Financial and Insurance Industry
Classifier: Intended Audience :: Healthcare Industry
Classifier: Topic :: Scientific/Engineering
Classifier: Topic :: Scientific/Engineering :: Visualization
Classifier: Topic :: Software Development :: Build Tools
Classifier: Topic :: Software Development :: Libraries :: Python Modules
Classifier: Framework :: IPython
Classifier: Programming Language :: Python :: 3
Classifier: Programming Language :: Python :: 3.10
Classifier: Programming Language :: Python :: 3.11
Classifier: Programming Language :: Python :: 3.12
Requires-Python: >=3.10
License-File: LICENSE.txt
Requires-Dist: pandas >=2.1.0
Requires-Dist: numpy >=1.26.2
Requires-Dist: matplotlib >=3.8.2
Requires-Dist: seaborn >=0.13.0
Requires-Dist: scipy >=1.11.4
Requires-Dist: Jinja2 >=3.1.2
Requires-Dist: notebook >=7.0.6
Requires-Dist: wordcloud >=1.8.1
Requires-Dist: nltk >=3.6.7
